{"American Cola": "30", "Special Orange": "30", "Fruit Beer": "30", "Coffee Beer": "30", "Orange Beer": "30", "Masala Digest": "20", "Digest Ginger": "20", "Digest Lemon": "20", "Diet Minchina": "20", "Digest Orange": "20", "Avla Sarbat": "20", "Kokam": "20", "Limbu Sarbath Soda": "20", "Ice cream Soda": "15", "Ginger": "15", "Pineapple": "15", "Orange": "15", "Cola": "15", "Khus": "15", "Gulab Rose": "15", "Ras Beri": "15", "Jeera Soda": "15", "Lemon": "15", "Digestive Soda": "15", "Limbu Sarabat": "15", "Soda": "10", "Double Decker Ice cream Ball": "40", "Three in One Ice cream Ball": "25", "Strawberry Ice cream Ball": "25", "Chocolate Ice cream Ball": "25", "Pista Ice cream Ball": "25", "Mango Ice cream Ball": "25", "Cake Cream Ice cream Ball": "30", "Vanilla Ice cream Ball": "25", "Triple Dip Cone": "40", "Cornetto": "30", "Deluxe Milkcold": "90", "American Shake": "90", "Anjeer Shake": "70", "Badamthandai Shake": "70", "Pista Shake": "70", "Mango Shake": "70", "Chocolate Shake": "70", "Banana Shake": "70", "Rose Shake": "70", "Strawberry Shake": "70", "Apple Shake": "70", "Chikoo Shake": "70", "Black Current Shake": "70", "Cold Coffee": "70", "Butterscotch Shake": "70", "American Corn Float": "50", "American Lemon Float": "50", "Milk Cold Drink with Ice cream": "70", "Milk Cooldrink": "60", "Fruit Salad Sandwich": "120", "Lovers Favorite": "150", "Cocktail I Cream": "130", "Fruit Jam": "90", "Fruit Jelly": "90", "Fruit Salad": "75", "Salad with Cream": "60", "Jam Ice cream": "40", "Pulp with Ice cream": "40", "Lemon Crush": "30", "Pineapple Crush": "30", "Orange Crush": "30", "Mangolin Crush": "30", "Mava Kulfi": "25", "Matka Kulfi": "35", "Choco Bar": "20", "Special Cocktail": "160", "Special Fruit Salad": "110", "Special Fruit Jam": "120", "Special Fruit Jelly": "120", "Vanilla Mastani": "100", "Mango Mastani": "120", "Strawberry Mastani": "120", "Pista Mastani": "120", "Deluxe Mastani": "120", "Butterscotch Salt Mastani": "120", "Choco Mastani": "120", "Deluxe Lassi": "60", "Lassi with Ice cream": "40", "Kaju Badam Lassi": "50", "Mango Lassi": "40", "Lassi": "30", "Pineapple Desert": "120", "Apple Desert": "120", "Mixed Desert": "120", "Chikoo Desert": "120", "Cocktail Juice": "70", "Apple Juice": "70", "Mango Juice": "70", "Chikoo Juice": "70", "Mini Chocobar": "10", "Mini Kulfi": "15", "Mineral Water": "20", "Kasata": "200", "Raj Bhog": "115", "Choco Dove": "115", "Marble": "110", "Anjeer": "115", "Kaju Kismis": "110", "Chocolate": "110", "Mango": "110", "Butterscotch Scotch": "110", "Badam Pista": "110", "Magic Sundae": "110", "Vanilla": "100", "Deluxe Cassata Ice cream": "70", "Rajbhog Ice cream": "50", "Kaju Kismis Ice cream": "50", "Butterscotch Ice cream": "50", "Mango Ice cream": "50", "Chocolate Ice cream": "50", "Anjeer Ice cream": "50", "Badam Pista Ice cream": "50", "Marbal Ice cream": "50", "Vanilla Ice cream": "40", "Anjir Falooda": "80", "Butterscotch Falooda": "80", "Kulfi Falooda": "80", "Deluxe Falooda": "80", "Bombay Falooda": "70"}