{"Plain Thali": "105", "Delux Thali": "125", "Golden Thali": "180", "Mineral Water (500 ml)": "20", "Sweet (Chefs Choice)": "15", "Aloo Paratha": "30", "Gobi Paratha": "30", "Paneer Paratha": "40", "Mixed Paratha": "40", "Mithi Paratha (Session Types)": "40", "Onion Paratha": "25", "Muli Paratha": "25", "Paneer Nan": "40", "Stuffeded Paratha": "40", "Laccha Paratha": "30", "Plain Paratha": "20", "Plain Butter Paratha": "15", "Veg Manchurian": "90", "Chilli Paneer": "120", "Chilli Mushroon": "120", "Paneer 65": "110", "Paneer Manchurian": "120", "Paneer Roghan Josh": "90", "Paneer Kashmiri Kofta": "120", "Mixed Veg": "60", "Dum Aloo Kashmiri": "100", "Seasonal Sabji": "30", "Masala Dum Aloo": "60", "Mushroom Mattar": "60", "Malai Kofta": "70", "Mushroom Masala": "60", "Tamatar Masala": "60", "Chana Masala": "50", "Shimla Stuffed": "80", "Stuffed Tamatar": "80", "Veg Kofta": "70", "Sev Masala": "80", "Sev Tomato": "70", "Sev Fried Rice": "90", "Veg Pulao": "90", "Steamed Rice": "40", "Paneer Changeji": "180", "Paneer Lababdar": "160", "Cumin Rice": "55", "Tandoori Roti": "5", "Tandoori Butter Roti": "7", "Missi Roti": "15", "Tawa Rott": "5", "Tawa Roti Butter": "8", "Plain Roti": "20", "Green Salad": "40", "Tomato Salad": "30", "Onion Salad": "20", "Kachumar Salad": "40", "Paneer Pulao": "120", "Masala Pulao": "90", "Mushroom Pulao": "120", "Mushroom Biryani": "140", "Butter Jeera Rice with Paneer": "80", "Veg Biryani": "90", "Plain Rice": "40", "Jeera Rice": "35", "Masala Rice": "40", "Boondi Raita": "20", "Dahi": "15", "Plain Dal": "30", "Dal Tadka": "40", "Dal Fry": "30", "Dal Special Fry": "50", "Dal Bharta Butter": "70", "Dal Mughlai": "80", "Dal Basanti": "70", "Papad Masala": "120", "Papad Dry": "6", "Papad Fry": "10", "Shahi Paneer": "90", "Butter Paneer": "100", "Kadai Paneer": "100", "Paneer Mushroom": "90", "Paneer Pasanda": "160", "Paneer Tikka Masala": "160", "Kaju Paneer": "120", "Mattar Paneer": "50", "Special Mattar Paneer": "70", "Palak Paneer": "50", "Paneer Handi": "90", "Paneer Bhurji": "90", "Paneer Korma": "90", "Paneer Do Pyaza": "90", "Kaju Curry": "90", "Kaju Masala": "90", "Paneer Mughlai": "120", "Paneer Makhani": "100", "Paneer Jaipuri": "120", "Paneer Malmal": "130", "Paneer Kaleji": "140", "Paneer Tawa Masala": "150", "Paneer Tamatar": "70", "Paneer Kolhapuri": "160", "Jeera Aloo": "80", "Lentil Fry": "40", "Lentil Fry Special": "55"}