{"Veg Steamed Momos": "60", "Veg Fried Momos": "75", "Paneer Steamed Momos": "90", "Paneer Fried Momos": "105", "Veg Tadka Momos": "90", "Paneer Tadka Momos": "120", "Veg Gravy Momos": "105", "Paneer Gravy Momos": "135", "Spring Rolls": "75", "Veg Cutlet": "135", "French Fries": "90", "Red Sauce Penne Pasta": "195", "White Sauce Penne Pasta": "210", "Double Sauce Penne Pasta": "240", "Maggi": "60", "Fresh Sandwich": "45", "Green Sandwich": "60", "Bread Pakora": "30", "Paneer Bread Pakora": "38", "Aloo Pakora": "390", "Onion Pakora": "345", "Paneer Pakora": "450", "Palak Pakora": "360", "Mixed Pakora": "405", "Chutney Samosa": "15", "Chole Bhature": "75", "Aloo Poori Sabji": "105", "Chole Poori Sabji": "120", "Boondi Raita": "75", "Palak Raita": "90", "Kheer Raita": "75", "Carrot Raita": "90", "Mixed Veg Raita": "105", "Special Milk Tea": "45", "Black Tea": "30", "Lemon Tea": "38", "Hot Coffee": "45", "Cold Coffee": "75", "Sweet Hot Milk": "60", "Lassi": "30", "Meethi Lassi": "60", "Masala Lassi": "45", "Dahi": "30", "Meethi Dahi": "60", "Masala Dahi": "45", "Banana Shakes": "75", "Mango Shakes": "90", "Chocolate Shakes": "75", "Apple Shakes": "105", "Banana Milkshake": "105", "Mango Milkshake": "105", "Chocolate Milkshake": "105", "Apple Milkshake": "105", "Veg Burger": "38", "Aloo Tikki Burger": "45", "Chow mein Burger": "60", "Cream Burger": "68", "Paneer Burger": "75", "Double Tikki Burger": "90", "Special Burger": "105", "Veg Chow mein": "60", "Garlic Chow mein": "75", "Cheese Chow mein": "90", "Paneer Chow mein": "105", "Mix Chow mein": "120", "Hakka Noodles": "135", "Singapuri Chow mein": "150", "Manchurian Dry": "75", "Manchurian Gravy": "120", "Paneer Manchurian Dry": "135", "Paneer Manchurian Gravy": "150", "Chi Chilli": "120", "Chilli Potato": "105", "Chilli Honey Potato": "135", "Chilli Honey Gobi": "90", "Chilli Paneer": "135", "Mushroom Chilli": "150", "Chole Rice": "120", "Dal Rice": "135", "Rajma Rice": "150", "Veg Fried Rice": "165", "Paneer Fried Rice": "180", "Manchurian Fried Rice": "195", "Paneer Manchurian Rice": "210", "Veg Pulao": "165", "Paneer Pulao": "195", "Veg Biryani": "165", "Paneer Biryani": "210", "Palak Paneer": "165", "Kadai Paneer": "180", "Mattar Paneer": "195", "Shahi Paneer": "225", "Malai Kofta": "210", "Paneer Bhurji": "240", "Aloo Palak": "120", "Jeera Aloo": "120", "Dum Aloo": "195", "Aloo Gobi": "165", "Aloo Mattar": "150", "Aloo Methi": "135", "Mixed Veg": "255", "Dal Tadka": "150", "Dal Makhani": "195", "Dal Fry": "165", "Rajma": "165", "Chole": "150", "Mushroom Sabji": "210", "Mattar Mushroom": "240", "Mushroom Masala": "195", "Paneer Mushroom": "270", "Tawa Plain Roti": "15", "Tawa Butter Roti": "18", "Plain Tandoori Roti": "20", "Tandoori Butter Roti": "23", "Missi Roti": "30", "Pyaaz Roti": "38", "Plain Naan": "30", "Butter Naan": "45", "Garlic Naan": "53", "Pudina Naan": "60", "Aloo Naan": "53", "Stuffed Naan": "75", "Plain Paratha": "30", "Aloo Paratha": "60", "Onion Paratha": "45", "Laccha Paratha": "73", "Paneer Paratha": "90", "Mixed Paratha": "90", "Stuffed Paratha": "105", "Green Salad": "90", "Cream Salad": "135", "Simple Thali": "120", "Thali with Rice": "180", "Missi Roti Thali": "240", "Butter Naan Thali": "270", "Chaudhary Restaurant Special Thali": "450"}