{"Soda": "75", "Fresh Fruit Salad": "170", "Gulab Jamun": "135", "Rasgulla (2 Pcs)": "135", "Toasted Chutney Sandwich": "160", "Toasted Vegetable Sandwich": "210", "Toasted Boiled Egg Sandwich": "195", "Toasted Omelette Sandwich": "195", "Toasted Veg Club Sandwich": "225", "Toasted Chicken Club Sandwich": "245", "Toasted Chicken Mayo Sandwich": "215", "Toasted Chicken and Cheese Sandwich": "230", "Plain Chutney Sandwich": "160", "Plain Vegetable Sandwich": "210", "Plain Boiled Egg Sandwich": "195", "Plain Omelette Sandwich": "195", "Plain Veg Club Sandwich": "225", "Plain Chicken Club Sandwich": "245", "Plain Chicken Mayo Sandwich": "215", "Plain Chicken and Cheese Sandwich": "230", "Grilled Chutney Sandwich": "160", "Grilled Vegetable Sandwich": "210", "Grilled Boiled Egg Sandwich": "195", "Grilled Omelette Sandwich": "195", "Grilled Veg Club Sandwich": "225", "Grilled Chicken Club Sandwich": "245", "Grilled Chicken Mayo Sandwich": "215", "Grilled Chicken and Cheese Sandwich": "230", "French Fries": "175", "Garlic Toast": "150", "Baked Bean Toast": "150", "Chilli Cheese Toast": "210", "Three Bell Pepper Toast": "195", "Cheese Balls": "210", "Vegetable Cutlets": "225", "Mutton Cutlets": "260", "Chicken Cutlets": "250", "Mix Veg Pakoras": "210", "Paneer Pakoras": "220", "Fish & Chips": "350", "Fish Cutlets": "350", "Fish Fingers": "350", "Prawn Chilli": "390", "Prawn Schezwan": "390", "Prawn Garlic ": "390", "Chicken Chilli Dry": "360", "Chicken Garlic Dry": "360", "Chicken Schezwan Dry": "360", "Crispy Fried Chicken": "370", "American Chop suey in Crispy Fried Noodles": "290", "Vegetable Schezwan": "260", "Vegetable Manchurian": "260", "Gobi Manchurian": "260", "Sweet and Sour Vegetable": "260", "Paneer Chilli": "290", "Vegetable Pizza": "225", "Chicken Pizza": "235", "Mutton Pizza": "240", "Mix Pizza": "275", "Prawn Fried Rice": "360", "Nasi Goreng Chicken": "380", "Nasi Goreng Prawn": "380", "Chicken Fried Rice": "310", "Schezwan Chicken Fried Rice": "325", "Egg Fried Rice": "275", "Veg Fried Rice": "250", "Veg Hakka Noodles": "250", "Mixed Fried Rice": "400", "Hakka Noodles": "400", "Chicken Roast": "345", "Chicken Stroganoff": "345", "Chicken Ratatouille": "345", "Chicken Escalopes": "325", "Chicken Stew": "325", "Arrabbiata Penne Pasta": "280", "Arrabbiata Spaghetti Pasta": "280", "Penne in Cream & Cheese Sauce": "280", "Spaghetti in Cream & Cheese Sauce": "280", "Penne in Spinach & Cream Sauce": "280", "Spaghetti in Spinach & Cream Sauce": "280", "Penne Pasta Sicilian": "280", "Vegetable Au gratin": "280", "Spaghetti Napolitano": "280", "Ajwain Tawa": "75", "Pudina Tawa": "75", "Methi Tawa": "75", "Chapati (2 Pcs)": "70", "Garlic Naan": "95", "Plain Naan": "75", "Butter Naan": "95", "Cheese Naan": "95", "Tandoori Roti": "60", "Methi Roti": "60", "Pudina Roti": "60", "Ajwain Paratha Tandoor": "75", "Pudina Paratha Tandoor": "75", "Methi Paratha Tandoor": "75", "Vegetable Stuffed Kulcha": "125", "Paneer Stuffed Kulcha": "125", "Aloo Stuffed Kulcha": "125", "Vegetable Paratha": "125", "Paneer Paratha": "125", "Aloo Paratha": "125", "Stuffed Keema Paratha": "190", "Raita": "130", "Plain Curd": "120", "Fish Florentine": "390", "Fish Steak": "390", "Ratatouille Fish": "390", "Ratatouille Prawn": "410", "Chicken Steak": "325", "Pomfret Fish Biryani": "475", "Fish Biryani": "410", "Prawn Biryani": "425", "Chicken Biryani": "350", "Mutton Gosht Biryani": "390", "Mutton Pulao": "390", "Subji Biryani": "275", "Subji Pulao": "275", "Safed Chawal": "160", "Egg Biryani": "250", "Egg Pulao": "250", "Fish Majboos": "415", "Lamb Majboos": "425", "Chicken Majboos": "375", "Moong Dal Khichdi": "225", "Malai Kofta": "280", "Navratan Korma": "280", "Paneer Butter Masala": "290", "Paneer Makhani": "290", "Palak Paneer": "280", "Paneer Bhurji": "280", "Vegetable Jalfrezi": "275", "Vegetable Makhani": "275", "Yellow Dal Fry": "210", "Dal Makhani": "225", "Tadke Wali Dal": "210", "Goan Fish Curry": "410", "Pomfret Masala": "410", "Fish Curry": "350", "Prawn Curry": "410", "Prawn Masala": "410", "Aloo Gobi Mattar": "240", "Aloo Palak": "240", "Aloo Jeera": "225", "Bhindi Fry": "225", "Chana Masala": "235", "Dum Aloo Kashmiri": "240", "Dahi Kadi Pakora": "225", "Dhingri Mattar": "260", "Mix Vegetable Curry": "240", "Baingan Bharta": "235", "Butter Chicken": "310", "Murgh Shajahani": "310", "Chicken Curry": "290", "Chicken Jalfrezi": "325", "Chicken Saagwala": "290", "Murgh Peshwari": "310", "Chicken Roghani": "310", "Chicken Nashik": "350", "Chicken Suba Special": "410", "Mutton Rogan Josh": "375", "Mutton Curry": "375", "Shahi Mutton Korma": "375", "Mutton Vindaloo": "375", "Mutton Bhuna ": "375", "Mutton Do Pyaza": "375", "Mutton Dal Gosht": "350", "Mutton Nashik": "395", "Laziz Tikka Masala": "340", "Pomfret Fry": "435", "Chinese Golden Fried Prawn": "410", "Fish Fry": "410", "Grilled Fish": "410", "Grilled Prawn": "410", "Chatpata Aloo": "160", "Channa Chaat": "160", "Waldorf Salad": "225", "Tossed Salad": "160", "Spicy Pineapple Salad": "180", "Classical Chicken Ceasar Salad": "240", "Russian Salad": "225", "Greek Salad": "210", "Green Salad": "210", "Fattoush": "210", "Moutabel": "210", "Babaganouj": "210", "Hummus": "195", "Shorba Harira": "190", "Shorba Aadas Maa Sabanik": "180", "Shorba Al Jajar": "180", "Shorba Khada": "180", "Mushroom Soup": "180", "Vegetables Soup": "180", "Spinach Soup": "180", "Chicken Soup": "180", "Tomato Soup": "180", "Minestrone Soup": "180", "Vegetable Hot & Sour Soup": "180", "Chicken Hot & Sour Soup": "180", "Vegetable Clear Soup": "160", "Dal Dhaniya Shorba": "180", "Vegetable Sweet corn Soup": "180", "Chicken Sweet corn Soup": "180", "Vegetable Noodles Soup": "180", "Chicken Noodles Soup": "180", "Vegetable Manchow Soup": "180", "Chicken Manchow Soup": "180", "French Soup": "180", "Arabic Lentil Soup": "180", "Omelette": "180", "Fried Egg": "180", "Poached Egg": "180", "Scrambled Egg": "180", "Boiled Egg": "180", "Laal Mirch ki Pomfret": "445", "Fish Tikka": "395", "Tandoori Khazana": "675", "Tangdi Kebab": "260", "Murgh Malai Kebab": "310", "Chicken Tikka": "325", "Tandoori Chicken": "350", "Chicken Reshmi Kebab": "325", "Mutton Seekh Kebab": "365", "Lal Mirch ka Paneer Tikka": "310"}