{"Malabar Paratha (1 No)": "65", "Idiyappam (3 Nos)": "95", "Steam Dosa (2 Nos)": "80", "Egg Appam (1 No)": "80", "Appam (1 No)": "50", "Seafood Chowder": "165", "Seafood  Clear Soup": "165", "Nandu Rasam": "145", "Prawn Manchow Soup": "165", "Hot & Sour Prawn Soup": "165", "Spicy Prawn Soup": "165", "Nethili Fry": "230", "Vanjaram Fry": "350", "Babycorn salt & Pepper": "210", "Crispy Fried Vegetable": "200", "Chilli Mushroom": "215", "Gobi Manchurian": "210", "Tandoori Gobi": "210", "Tandoori Mushroom": "215", "Vegetable Sheek Kebab": "215", "Paneer Tikka": "265", "Mutton Coconut Fry": "350", "Mutton Pepper Fry": "350", "Crispy Chilli Lamb": "350", "Chicken Kalimirchi Kebab": "295", "Tandoori Chicken": "450", "Chicken Malai Kebab": "295", "Chicken Tikka": "295", "Chicken Pepper Fry": "295", "Chilli Chicken": "295", "Dragon Chicken": "275", "Chicken Lollypop": "295", "Chicken 65": "275", "Chilli Prawns": "375", "Tandoori Prawn": "350", "Golden Fried Prawn": "375", "Butter Garlic Prawn": "375", "Prawn Pepper Fry": "350", "Crispy Fried Prawn": "375", "Masala Fried Prawn": "375", "King Prawn": "635", "Fish Manchurian": "325", "Phuket Fish": "325", "Fish Tikka": "325", "Fish Pepper Fry": "325", "Chilli Fish": "325", "Fish finger": "325", "Mackerel Fry": "230", "Lady Fish Fry": "265", "Amritsari Fish": "315", "Green Salad": "95", "Indian Tossed Salad": "95", "Coastline Special Chicken Salad": "140", "Coastline Special Seafood Salad": "180", "Phulka": "50", "Tandoori Paratha": "60", "Kulcha": "65", "Butter Naan": "65", "Naan": "50", "Egg Fried Rice": "200", "Garlic Naan": "65", "Roti": "50", "Vegetable Fried Rice": "180", "Seafood Fried Rice": "375", "Prawn Fried Rice": "350", "Chicken Fried Rice": "205", "Vegetable Biryani": "220", "Seafood Biryani": "385", "Prawn Biryani": "385", "Mutton Biryani": "330", "Chicken Biryani": "275", "Dal Tadka": "205", "Dal Makhni": "205", "Palak Paneer": "275", "Paneer Butter Masala": "275", "Aloo Mutter": "205", "Kadai Veg": "215", "Kadala Curry": "205", "Veg Stew": "205", "Mutton Roganjosh": "335", "Mutton Curry": "335", "Chicken Chettinad": "295", "Schezwan Chicken": "275", "Kadai Chicken": "280", "Butter Chicken Masala": "295", "Chicken Stew": "275", "Chicken Curry": "295", "Goan Prawn Curry": "375", "Fish Tikka Masala": "350", "Prawn Curry": "375", "Prawn Masala": "375", "Sear Fish Curry": "350", "Mackerel Curry": "230", "Lady fish Curry": "265", "Shankara Curry": "230", "Chilli Crab (Shell less)": "385", "Crab Podimas": "385", "Crab Lollypop": "385", "Squid Masala Fry": "295", "Squid Chilli Fry": "295", "Squid Pepper Fry": "295", "Chilli Squid": "295", "Crispy Fried Squid": "295", "Ada Prathaman": "110", "Fruit Salad": "110", "Gulab Jamun": "100", "Lassi": "90", "Butter Milk": "65", "Fresh Lime Soda": "50", "Fresh Lime Juice": "40"}