{"Gobi 65": "155", "Vellattu Sukka": "225", "Achari Paneer Tikka": "205", "Murgh Malai Kebab": "205", "Chettinad Yera Melagu Thokku": "255", "Dal Fry": "165", "Dal Fry with Jeera Pulao": "99", "Aloo Gobi Masala with Mutter Pulao": "129", "Subzi Meloni with Jeera Pulao": "139", "Kozhi Melagu Masala with Plain Biryani": "179", "Mutton Sukka Gravy with Mutter Pulao": "199", "Paneer Butter Masala with Mutter Pulao": "169", "Egg Masala with Jeera Rice": "99", "Mushroom Masala with Mutter Pulao": "169", "Chicken Tikka Masala with Jeera Rice": "189", "Kottayam Jinga Masala with Jeera Rice": "199", "Eco Tandoor Leg & Thigh": "139", "Eco Fish Finger (4 Pcs)": "139", "Eco Chicken 65": "139", "Eco Chicken Lollypop (4 Pcs)": "139", "Veg Thai Green Curry + Rice": "185", "Chicken Thai Red Curry + Rice": "205", "Chicken Thai Green Curry + Rice": "205", "Prawns Thai Red Curry + Rice": "245", "Prawns Thai Green Curry + Rice": "245", "Veg Thai Red Curry + Rice": "185", "Masala Omelette": "95", "Cheese Omelette (2 Eggs)": "95", "Vegetable Quesadilla": "225", "Chicken Quesadilla": "245", "Veg Sweet corn Soup": "85", "Veg Cream Soup": "85", "Mushroom Cream Soup": "95", "Veg Hot & Sour Soup": "125", "Chicken Sweet corn Soup": "95", "Chicken Cream Soup": "95", "Kozhi Milagu Saaru": "105", "Lung Fung Chicken Soup": "145", "Chicken Hot & Sour Soup": "145", "Mutton Milagu Rasam": "105", "Veg Caesar Salad": "185", "Greek Salad": "165", "Veg Hawaiian Salad": "185", "Veg Pasta Salad": "155", "Chicken Caesar Salad": "205", "Chicken Hawaiian Salad": "205", "Chicken Pasta Salad": "185", "Prawns Caesar Salad": "225", "Prawns Pasta Salad": "205", "11\" Margherita Pizza": "345", "11\" Tandoor Paneer Pizza": "345", "11\" Rustica Pizza": "345", "11\" Mushroom and Cheese Pizza": "345", "11\" Cheese and Onion Pizza": "345", "11\" Exotic Vegetable Pizza": "345", "11\" American BBQ Pizza": "395", "11\" Chicken Tikka Pizza": "395", "11\" Italian Fantasy Pizza": "395", "11\" Mexican Blast Pizza": "395", "11\" Chicken Bolognese Pizza": "395", "11\" Devilled Chicken Pizza": "395", "11\" Hawaiian Chicken Pizza": "395", "Alfredo Pasta": "285", "Arrabiatta Pasta": "285", "Pesto Pasta": "285", "Pomodoro Formaggio Pasta": "285", "A La Romana Pasta": "305", "Bolognaise Pasta": "305", "Frutti Di Marie Pasta": "335", "Chicken Lasagne": "305", "Baby corn Bezue": "165", "Kalan Podi Varuval": "165", "Mushroom 65": "165", "Paneer 65": "165", "Idicha Kozhi Varuval": "195", "Palli Palayam Chicken": "195", "Guntur Kodi Vepudu": "195", "Malli Chicken": "195", "Chicken 65": "195", "Mutton Ularthiyathu": "225", "Fish 65": "195", "Chemeen Porichadu": "245", "Royalla Vepudu": "245", "Paneer Tikka Lehsuni": "205", "Tandoori Chicken": "235", "Chicken Achari Tikka": "205", "Murgh Tangdi Kebab": "205", "Machli Tikka": "355", "Tandoori Jinga": "405", "Tandoori Platter": "325", "Kadai Paneer": "195", "Methi Paneer": "195", "Paneer Makhanwala": "195", "Kofta Bukhara": "195", "Sabji Meloni": "185", "Dum Aloo Pudinawale": "195", "Aloo Gobi Masala": "195", "Khumb Mattar Hare Pyaza": "195", "Kalan Milagu Masala": "195", "Egg Masala": "175", "Kozhi Milagu Masala": "205", "Chettinad Chicken Masala": "205", "Kozhi Varutha Curry": "205", "Chicken Tikka Masala": "205", "Butter Chicken Masala": "205", "Methi Chicken": "205", "Ginger Chicken Masala": "205", "Mutton Chettinad": "245", "Mutton Pepper Masala": "245", "Mutton Varutha Curry": "245", "Mutton Rogan Josh": "245", "Nelore Chapala Koora": "245", "Kottayam Jhinga Masala": "255", "Dal Tadka": "165", "Veg Biryani": "165", "Egg Biryani": "165", "Chicken Biryani": "185", "Mutton Biryani": "205", "Choice of Pulao": "155", "Vadi Saadham": "75", "Thayir Saadham": "105", "Plain Naan": "65", "Butter Naan": "75", "Garlic Naan": "85", "Tandoori Roti": "55", "Butter Roti": "65", "Aloo Paratha": "105", "Laccha Paratha": "95", "Plain Kulcha": "75", "Onion Kulcha": "95", "Paneer Kulcha": "95", "Masala Kulcha": "95", "Cheese Kulcha": "95", "Dimora Fries": "175", "Crispy Corn Poppers": "185", "Gobi Manchurian": "155", "Devilled Gobi": "155", "Gobi Salt & Pepper": "155", "Devilled Mushroom": "165", "Mushroom Manchurian": "165", "Mushroom Salt & Pepper": "165", "Paneer Manchurian": "165", "Devilled Paneer": "165", "Paneer Salt & Pepper": "165", "Schezwan Baby corn": "165", "Schezwan Paneer": "165", "Breaded Mushroom": "185", "Chicken Lollipop - Schezwan Style": "195", "Crispy Chicken Wings": "195", "Hot Chicken Wings": "195", "Devilled - Chicken": "195", "Chicken Lollipop Dry": "195", "Chilli Chicken": "195", "Chicken Manchurian": "195", "Schezwan Chicken": "195", "Dragon Chicken": "195", "Peri Peri Chicken Wings": "225", "Dimora Fried Chicken": "225", "Shredded Lamb in Black Pepper": "255", "Devilled - Fish": "225", "Chilli Fish": "225", "Fish Fingers": "255", "Dragon Fish": "225", "Fish Manchurian": "225", "Schezwan Fish": "225", "Singapore Chilli Prawn": "245", "Devilled - Prawn": "245", "Chilli Prawns": "245", "Prawns Manchurian": "245", "Schezwan Prawns": "245", "Dragon Prawns": "245", "Stir Fried Vegetable": "165", "Gobi Manchurian Gravy": "165", "Gobi Chilli Gravy": "165", "Paneer Manchurian Gravy": "175", "Paneer Chilli Gravy": "175", "Mushroom Manchurian Gravy": "175", "Mushroom Chilli Gravy": "175", "Baby corn Manchurian Gravy": "175", "Chilli Baby corn Gravy": "175", "Chicken Shanghai": "195", "Chicken Schezwan": "195", "Garlic Chicken": "195", "Manchurian Chicken": "190", "Sweet & Sour Chicken": "195", "Lamb in Oyster": "225", "Garlic Fish": "225", "Fish Schezwan": "225", "Fish Shanghai": "225", "Manchurian Fish": "225", "Sweet & Sour Fish": "225", "Sweet & Sour Prawns": "245", "Prawns Shanghai": "245", "Prawns Schezwan": "245", "Garlic Prawns": "245", "Manchurian Prawns": "245", "Stir Fry Veg Fried Rice": "165", "Schezwan Veg Fried Rice": "165", "Lifu Veg Fried Rice": "165", "Shanghai Veg Fried Rice": "165", "Stir Fry Chicken Fried Rice ": "185", "Schezwan Chicken Fried Rice ": "185", "Lifu Chicken Fried Rice ": "185", "Shanghai Fried Rice Chicken": "185", "Stir Fry Fish Fried Rice ": "225", "Schezwan Fish Fried Rice ": "225", "Lifu Fish Fried Rice ": "225", "Shanghai Fish Fried Rice ": "225", "Stir Fry Prawns Fried Rice ": "225", "Schezwan Prawns Fried Rice ": "225", "Lifu Prawns Fried Rice ": "225", "Shanghai Prawns Fried Rice ": "225", "Nasi Goreng": "245", "Stir Fry Veg Noodles ": "165", "Schezwan Veg Noodles ": "165", "Lifu Veg Noodles ": "165", "Shanghai Veg Noodles ": "165", "Stir Fry Chicken Noodles ": "185", "Schezwan Chicken Noodles ": "185", "Lifu Chicken Noodles ": "185", "Shanghai Chicken Noodles ": "185", "Stir Fry Fish Noodles ": "225", "Schezwan Fish Noodles ": "225", "Lifu Fish Noodles ": "225", "Shanghai Fish Noodles ": "225", "Stir Fry Prawns Noodles ": "225", "Schezwan Prawns Noodles ": "225", "Lifu Prawns Noodles ": "225", "Shanghai Prawns Noodles ": "225", "Vegetable Sizzler": "305", "Paneer Sizzler": "405", "Grilled Peri Peri Chicken Sizzler": "425", "Cajun Chicken Steak Sizzler": "425", "Fish Steak Sizzler": "435", "Prawns Sizzler": "455", "Tandoori Sizzler": "505", "Selection of Ice cream": "85", "Lychee with Ice cream": "155", "Fruit Salad": "165", "Hot Chocolate Brownie": "185", "Summer Sundae": "205", "Toffee Banana Crepes": "155", "Paris Wild Berry Crepes": "185", "Iranian Falooda": "205", "Orange Squeezed Juice": "105", "Sweet Lime Squeezed Juice": "105", "Apple Squeezed Juice": "105", "Water Melon Squeezed Juice": "105", "Carrot Squeezed Juice": "105", "Papaya Squeezed Juice": "105", "Watermelon & Ginger Cooler Mocktail": "115", "Papaya & Orange Delight Mocktail": "115", "Bright Eyes Mocktail": "115", "Detox Mocktail": "115", "Sweety Spirulina Mocktail": "115", "Blackcurrant Delight Mocktail": "115", "Hawaiian Sunshine Mocktail": "115", "Lychee Breezer Mocktail": "115", "Minty Mango Mocktail": "115", "Indian Summer Mocktail": "115", "Orange & Passion Fruit Mojito": "115", "Mojito Mocktail": "115", "Apple & Mint Collins Mocktail": "115", "Fruit Sensation Mocktail": "115", "Red Apple Fizz Mocktail": "115", "Infrared Mocktail": "115", "Blue Lagoon Mocktail": "115", "Roy Rogers Mocktail": "115", "Shirley Temple Mocktail": "115", "Plain Cold Coffee": "135", "Cold Coffee with Vanilla Ice cream": "145"}