{"Chicken Sweet Corn Soup": "150", "Chicken Hot & Sour Soup": "150", "Veg Monsoon Soup": "130", "Tomato Soup": "100", "Sweet Corn Soup": "100", "Hot & Sour Soup": "110", "Chilli Chicken": "180", "Chicken 65": "180", "Chicken Rayalaseema": "190", "Lemon Chicken": "190", "Chicken Majestic": "190", "Royal Chicken": "190", "Tiger Chicken": "190", "Chicken Roast": "140", "Chicken Lollipop (5 Pcs)": "190", "Natukodi Pulusu": "230", "Ginger Chicken": "160", "Chicken Curry": "150", "Butter Chicken": "180", "Chicken Mughlai": "190", "Dal Tadka": "130", "Dal Fry": "110", "Methi Dal": "120", "Palak Dal": "110", "Plain Palak": "110", "Palak Paneer": "170", "Kadai Paneer": "180", "Paneer Butter Masala": "190", "Paneer Tikka Masala": "160", "Mushroom Masala": "140", "Veg Hyderabad": "140", "Mixed Veg Curry": "150", "Veg Kadai Curry": "160", "Kaju Curry": "210", "Gobi Masala": "120", "Alu Gobi Masala": "130", "Baby Corn Curry": "150", "Veg Malai Kofta": "140", "Talakaya Kura": "200", "Mutton Curry Bone": "220", "Boneless Mutton Curry": "240", "Mutton Keema Curry": "230", "Mutton Roast Bone": "220", "Boneless Mutton Roast": "260", "Mutton Keema Ball (2)": "170", "Mutton Rogan Curry": "250", "Fish Curry (1)": "170", "Fish Fry (1)": "170", "Bommidayalu Pulusu": "230", "Prawns Curry": "220", "Prawns Fry": "240", "Prawns 65": "260", "Prawns Chilli": "250", "Egg Curry": "110", "Egg Chilli": "70", "Omelette": "60", "Chicken Biryani": "210", "Boneless Special Chicken Biryani": "250", "Mutton Biryani": "240", "Boneless Special Mutton Biryani": "280", "Prawns Biryani": "250", "Ragi Mudde": "50", "Chicken Fried Rice": "200", "Mutton Fried Rice": "250", "Prawns Fried Rice": "230", "Egg Fried Rice": "160", "Veg Fried Rice": "140", "Gobi Fried Rice": "140", "Singapore Fired Rice": "160", "Sangria Fried Rice": "180", "Kaju Fried Rice": "210", "Ghee Rice": "120", "Dry Fruits Fried Rice": "170", "Jeera Rice": "110", "Paneer Fried Rice": "170", "Schezwan Fried Rice": "160", "Mushroom Fried Rice": "170", "Baby Corn Fried Rice": "170", "Chicken Noodles": "170", "Mutton Noodles": "210", "Prawns Noodles": "210", "Egg Noodles": "130", "Veg Noodles": "140", "Gobi Noodles": "160", "American Noodles": "150", "Kaju Noodles": "210", "Dry Fruits Noodles": "180", "Schezwan Noodles": "160", "Noodle House Special": "160", "Mushroom Noodles": "160", "Paneer Noodles": "160", "Baby Corn Noodles": "170", "Jonna Roti (1)": "40", "Roti (1)": "35", "Butter Roti (1)": "45", "Naan (1)": "45", "Butter Naan (1)": "50", "Kulcha (1)": "40", "Butter Kulcha (1)": "45", "Groundnut Chutney": "60", "Aaku Kura Pappu": "80", "Qubani Ka Meetha": "80", "Butter Milk": "35", "Falooda": "60", "Strawberry Milk Shake": "80", "Vanilla Milk Shake": "80", "Black Current Milk Shake": "100", "Gobi Manchurian": "140", "Gobi 65": "140", "Gobi Chilli": "140", "Gobi Pepper Fry": "150", "Paneer 65": "170", "Paneer Chilli": "175", "Paneer Manchurian": "160", "Paneer Sholay Kabab": "170", "Paneer Pepper Dry": "170", "Paneer Mughlai Fry": "160", "Mushroom Mughlai Fry": "160", "Mushroom Chilli": "160", "Mushroom Manchurian": "160", "Mushroom Kebab": "150", "Mushroom Pepper Fry": "170", "Mushroom Monika": "170", "Baby Corn Chilli": "150", "Baby Corn Manchurian": "160", "Baby Corn Curry Leaves": "170", "Baby Corn Pepper Dry": "170", "Veg Manchurian": "140"}