{"Palak Paneer Dosa": "90", "Jain Palak Paneer Dosa": "100", "Cheese Palak Dosa": "100", "Jain Cheese Palak Dosa": "100", "Cheese Paneer Palak Dosa": "110", "Jain Cheese Paneer Palak Dosa": "120", "Masala Dosa": "70", "Jain Masala Dosa": "70", "Cheese Masala Dosa": "100", "Jain Cheese Masala Dosa": "100", "Cheese Sada Dosa": "70", "Cheese Paneer Sada Dosa": "80", "Mysore Masala Dosa": "80", "Jain Mysore Masala Dosa": "100", "Paneer Sada Dosa": "70", "Sada Dosa": "50", "Steam Idli": "60", "Medu Vada": "60", "Idli Vada": "60", "Pav Bhaji": "90", "Butter Pav Bhaji": "120", "Khada Pav Bhaji": "120", "Jain Pav Bhaji": "100", "Jain Butter Pav Bhaji": "120", "Tava Pulav": "90", "Jain Tava Pulav": "100", "Vada (4 Pcs)": "40", "Vada Pav (1 Pcs)": "20", "Paneer Cheese Pavbhaji": "150", "Chole Chaval": "90", "Kashmiri Pulav": "110", "Extra Pav": "10", "Bhel Puri": "50", "Sev Puri": "60", "Jain Sev Puri": "70", "Jain Bhel Puri": "60", "Dahi Puri": "70", "Jain Dahi Puri": "70", "Pani Puri": "40", "Papdi Chaat": "60", "Chole Bhature": "100", "Delhi Chaat": "80", "Dahi Bhale Chat": "80", "Extra Kulcha": "30", "Extra Bhatura": "30", "Extra Chole": "50", "8\" Special Pizza": "180", "8\" Margherita Pizza": "130", "8\" Italian Pizza": "150", "8\" Jain Pizza": "150", "Veg. Cheese Pizza": "140", "Veg Burger": "70", "Cheese Burger": "90", "Popcorn": "30", "French Fries": "50", "Plain Sandwich": "50", "Cheese Sandwich": "80", "Club Sandwich": "90", "Grill Sandwich": "70", "Jain Grill Sandwich": "80", "Cheese Grill Sandwich": "100", "Cheese Garlic Bread": "70", "Frankie": "50", "Cheese Frankie": "70", "Schezwan Cheese Frankie": "80", "Chinese Bhel": "90", "Veg Manchurian": "100", "Veg Hakka Noodles": "90", "Veg Fried Rice": "90", "Schezwan Fried Rice": "100", "Paneer Chilli": "140", "Mineral Water": "20", "Manchurian Rice": "100", "Singapuri Rice": "110", "Manchow Soup": "60", "Hot & Sour Soup": "60", "Fanta": "30", "Sprite": "30", "Coca Cola": "30", "Thumsup": "30", "Icecream Scoop": "30", "Kaju Pista Ice Cream": "30", "Real Mango Ice Cream": "30", "Chocolate Ice Cream": "30", "Butterscotch Ice Cream": "30", "Cherry Berry Ice Cream": "30", "Strawberry Ice Cream": "30", "Vanilla Ice Cream": "30", "Malai Kulfi": "20", "Pista Kulfi": "25", "Chocolate Kulfi": "25", "Badam Kulfi": "25", "Dry Fruit Kulfi": "35", "Khichu Surti": "30", "Locho Surti": "30", "Butter Lachha": "50", "Cheese Butter Lachha": "50", "Sweet Corn": "30", "Makai Bhel": "30", "Chana Chapati": "30", "Cheese Butter Makai Bhel": "50", "Aloo Puri": "30", "Cheese Aloo Puri": "50", "Kaju Anjeer": "100", "Kaju Gulkand Milkshake": "100", "Kaju Mango Milkshake": "100", "Kaju Chicku Milkshake": "100", "Kaju Cadbury Milkshake": "100", "Gulkand Milkshake": "80", "Strawberry Milkshake": "70", "Rose Milkshake": "70", "Pineapple Milkshake": "70", "Kesar Milkshake": "70", "Chiku Milkshake": "70", "Oreo Milkshake": "100", "Chocolate Milkshake": "70", "Cold Coco": "60", "Fruit Salad": "60", "Lassi": "60", "Badam Shake": "60", "Mix Icecream Badam": "100", "Mango Lassi": "70", "Chocolate Lassi": "70", "Rose Lassi": "70", "Strawbeery Lassi": "70", "Special Lassi": "60", "Mango Thick Shake": "110", "Pineapple Thick Shake": "110", "Rose Thick Shake": "110", "Kaju Anjeer Thik Shake": "120", "Gems Thik Shake": "110", "Cikkie Cream Thik Shake": "110", "Orio Thik Shake": "100", "Rabdi Faluda": "110", "Mango Faluda": "110", "Rose Faluda": "110", "Kesar Faluda": "110", "Chocolate Faluda": "110", "Mosambi Fresh Juice": "60", "Santara Fresh Juice": "60", "Pineapple Fresh Juice": "60", "Ganga Jamuna Saraswati": "70", "Ganga Jamuna": "70"}