{"Panneer Wrap": "95", "Panneer Sandwich": "85", "Fish Burger": "90", "Fish Nuggets": "105", "Fish Fingers": "94", "Corn Samosa": "60", "7\" Veg Filled Pizza": "109", "7\" Sweet Corn Pizza": "120", "7\" Paneer Pizza": "140", "7\" Mushroom Pizza": "140", "7\" Chicken Pizza": "160", "7\" Hot & Spicy Pizza": "140", "7\" Baby Corn Pizza": "150", "Veg Wrap": "70", "Chicken Wrap": "90", "Veg Sandwich": "60", "Sweet Corn Sandwich": "65", "Chicken Sandwich": "80", "Veg Burger": "60", "Veg Cheese Burger": "70", "Chicken Burger": "70", "Chicken Cheese Burger": "80", "Paneer Burger": "90", "French Fries": "60", "Potato Wedges": "80", "Veg Nuggets (5 Pcs)": "60", "Cheese Corn Nuggets (5 Pcs)": "70", "Chicken Nuggets (5 Pcs)": "80", "Chicken Bites (7 Pcs)": "80", "Chicken Finger (5 Pcs)": "80", "Chicken Samosa": "70", "Veg Roll (3 Pcs)": "60", "Paneer Roll (3 Pcs)": "80", "Chicken Roll (3 Pcs)": "80"}