{"Maharaja Thali ": "200", "Jain Thali ": "150", "Standard Thali ": "100", "Special Thali": "120", "Tea": "20", "Coffee": "30", "Milk": "40", "Butter Milk ": "20", "Lassi Sweet": "20", "Packed Drinking Water (1 ltr)": "20", "Fresh Lime Water": "20", "Lemon Tea": "20", "Green Salad ": "50", "Kachumber Salad": "50", "Onion Salad ": "30", "Papad Dry": "5", "Papad Fry": "10", "Papad Masala": "30", "Dal Fry": "80", "Dal Tadka ": "100", "Dal Handi": "100", "Butter Paneer Masala ": "150", "Shahi Paneer ": "150", "Chatpata Paneer": "150", "Bhurji Paneer ": "200", "Handi Paneer ": "150", "Paneer Pasanda ": "200", "Paneer Do Pyaza": "150", "Paneer Tikka Masala ": "200", "Kaju Paneer ": "200", "Mushroom Paneer ": "200", "Naman Special Paneer ": "250", "Palak Paneer": "150", "Mattar Paneer": "150", "Kaju Mushroom Paneer ": "250", "Kadai Paneer": "150", "Veg Kofta": "150", "Malai Kofta ": "150", "Nargisi Kofta ": "150", "Hariyali Kofta ": "150", "Paneer Kofta": "200", "Stuffed Tomato ": "120", "Stuffed Capsicum ": "120", "Aloo Dum": "120", "Aloo Dum Punjabi": "120", "Mixed Veg Masala": "100", "Aloo Mattar ": "100", "Aloo Jeera ": "80", "Aloo  Palak ": "100", "Aloo  Gobi ": "100", "Plain Palak ": "80", "Chana Masala": "120", "Mattar Masala": "120", "Bhindi Masala": "100", "Bhindi Do Pyaza": "120", "Veg Kadai ": "120", "Veg Kolhapur": "120", "Veg Mushroom Masala ": "200", "Kaju Curry": "200", "Veg Naman Special": "200", "Plain Rice": "50", "Jeera Rice ": "60", "Veg Biryani With Raita ": "120", "Hyderabadi Biryani With Raita ": "130", "Veg Pulao": "120", "Dal Khichdi ": "100", "Curd Rice": "100", "Veg Raita": "50", "Boondi Raita": "50", "Plain Curd": "50", "Tawa Roti": "5", "Buttered Roti ": "10", "Missi Roti": "30", "Plain Paratha": "20", "Tomato Soup": "70", "Veg Sweet Corn Soup ": "80", "Hot & Sour Soup": "80", "Veg Manchow Soup": "100", "Veg Chow mien ": "100", "Schezwan Noodles": "100", "Rice Noodles": "120", "Veg Fried Rice": "100", "Veg Dry Manchurian ": "120", "Veg Gravy Manchurian ": "130", "Paneer Dry Manchurian ": "150", "Paneer Gravy Manchurian ": "150", "Paneer Chilli Dry": "150", "Paneer Chilli Gravy ": "150", "Mushroom Chilli ": "150", "Mushroom Fried Rice  ": "150", "Mushroom Noodles ": "150", "Veg Kothey": "120", "Triple Fried Rice ": "160"}