{"Oil Locho": "65", "Cheese Butter Locho": "80", "Oil Dhokla": "60", "Masala Fry Dhokla": "75", "Oil Idada": "60", "Masala Fry Idada": "70", "Butter Locho": "75", "Red Garlic Locho": "80", "Special Masala Fry Locho": "85", "Butter Dhokla": "65", "Cheese Dhokla": "70", "Cheese Butter Dhokla": "80", "Cheese Idada": "65", "Butter Edada": "65", "Cheese Butter Edada": "75", "Masala Patra": "60", "Cheese Patra": "75", "Special Mayonnaise Patra": "85", "Special Masala Fry Patra": "70", "Plain Patra Vata": "80", "Lauki Handavo": "80", "Cheese Lauki Handavo": "90", "Mayonnaise Lauki Handavo": "100", "Methi Handavo": "80", "Cheese Methi Handavo": "90", "Mayonnaise Methi Handavo": "100", "Sabudana Khichdi": "70", "Faradi Patra": "70", "Combo 1": "180", "Combo 2": "199", "Combo 3": "180", "Combo 6": "214", "Dahi": "37", "Butter Milk": "23", "Patel Special Butter Milk": "43", "Mineral Water": "24", "Live Khamani": "85", "Cheese Khamani": "75", "Brunch 5": "162", "Brunch 4": "140", "Brunch 3": "135", "Brunch 2": "130", "Brunch 1": "125", "Brunch 6": "157", "Garlic Khaman": "60", "Special Cheese Masala Fry Khaman": "80", "Masala Khaman": "50", "Cheese Khaman": "60", "Cheese Garlic Khaman": "65", "Special Masala Fry Khaman": "70", "Wagharela Khaman": "55"}