{"7\" Jain Cheese Pizza (4 Slices)": "110", "9\" Jain Cheese Pizza (6 Slices)": "290", "12\" Jain Cheese Pizza (8 Slices)": "420", "7\" Jain Margherita's Favourite Pizza (4 Slices)": "110", "9\" Jain Margherita's Favourite Pizza (6 Slices)": "290", "12\" Jain Margherita's Favourite Pizza (8 Slices)": "420", "7\" Jain Simply Veg Pizza (4 Slices)": "150", "9\" Jain Simply Veg Pizza (6 Slices)": "420", "12\" Jain Simply Veg Pizza (8 Slices)": "510", "7\" Veg Treat Pizza (4 Slices)": "150", "9\" Veg Treat Pizza (6 Slices)": "420", "12\" Veg Treat Pizza (8 Slices)": "510", "7\" Any 3 Veggies Pizza (4 Slices)": "150", "9\" Any 3 Veggies Pizza (6 Slices)": "420", "12\" Any 3 Veggies Pizza (8 Slices)": "510", "7\" Jain Goodness Pizza (4 Slices)": "150", "9\" Jain Goodness (6 Slices)": "420", "12\" Jain Goodness (8 Slices)": "510", "7\" Jain Farm Fresh Pizza (4 Slices)": "150", "9\" Jain Farm Fresh Pizza (6 Slices)": "420", "12\" Jain Farm Fresh Pizza (8 Slices)": "510", "7\" Spicy Veggies Pizza (4 Slices)": "150", "9\" Spicy Veggies Pizza (6 Slices)": "420", "12\" Spicy Veggies Pizza (8 Slices)": "510", "7\" Cheese & Fries Pizza (4 Slices)": "175", "9\" Cheese & Fries Pizza (6 Slices)": "365", "12\" Cheese & Fries Pizza (8 Slices)": "530", "7\" Peri Peri Fries Pizza (4 Slices)": "175", "9\" Peri Peri Fries Pizza (6 Slices)": "365", "12\" Peri Peri Fries Pizza (8 Slices)": "530", "7\" Mumbai Pizza (4 Slices)": "220", "9\" Mumbai Pizza (6 Slices)": "490", "12\" Mumbai Pizza (8 Slices)": "590", "7\" Paneer Tikka Pizza (4 Slices)": "220", "9\" Paneer Tikka Pizza (6 Slices)": "490", "12\" Paneer Tikka Pizza (8 Slices)": "590", "7\" BBQ Paneer Pizza (4 Slices)": "220", "9\" BBQ Paneer Pizza (6 Slices)": "490", "12\" BBQ Paneer Pizza (8 Slices)": "590", "7\" Bianca Pizza (4 Slices)": "220", "9\" Bianca Pizza (6 Slices)": "490", "12\" Bianca Pizza (8 Slices)": "590", "7\" Hot Head Pizza (4 Slices)": "220", "9\" Hot Head Pizza (6 Slices)": "490", "12\" Hot Head Pizza (8 Slices)": "590", "7\" Jain Tasty Paneer Pizza (4 Slices)": "220", "9\" Jain Tasty Paneer Pizza (6 Slices)": "490", "12\" Jain Tasty Paneer Pizza (8 Slices)": "590", "7\" Chicken Salami Pizza (4 Slices)": "165", "9\" Chicken Salami Pizza (6 Slices)": "390", "12\" Chicken Salami Pizza (8 Slices)": "510", "7\" Spicy Sausage Pizza (4 Slices)": "165", "9\" Spicy Sausage Pizza (6 Slices)": "390", "12\" Spicy Sausage Pizza (8 Slices)": "510", "7\" Chicken Onion Pizza (4 Slices)": "165", "9\" Chicken Onion Pizza (6 Slices)": "390", "12\" Chicken Onion Pizza (8 Slices)": "510", "7\" Original BBQ Chicken Pizza (4 Slices)": "250", "9\" Original BBQ Chicken Pizza (6 Slices)": "445", "12\" Original BBQ Chicken Pizza (8 Slices)": "555", "7\" Chicken Tikka Pizza (4 Slices)": "250", "9\" Chicken Tikka Pizza (6 Slices)": "445", "12\" Chicken Tikka Pizza (8 Slices)": "555", "7\" Jalapeno Chicken Pizza (4 Slices)": "250", "9\" Jalapeno Chicken Pizza (6 Slices)": "445", "12\" Jalapeno Chicken Pizza (8 Slices)": "555", "7\" Peri Peri Chicken Pizza (4 Slices)": "250", "9\" Peri Peri Chicken Pizza (6 Slices)": "445", "12\" Peri Peri Chicken Pizza (8 Slices)": "555", "7\" Classic Chicken Pizza (4 Slices)": "250", "9\" Classic Chicken Pizza (6 Slices)": "445", "12\" Classic Chicken Pizza (8 Slices)": "555", "7\" Mushroom Chicken Pizza (4 Slices)": "250", "9\" Mushroom Chicken Pizza (6 Slices)": "445", "12\" Mushroom Chicken Pizza (8 Slices)": "555", "7\" Chicken Reward Pizza (4 Slices)": "300", "9\" Chicken Reward Pizza (6 Slices)": "510", "12\" Chicken Reward Pizza (8 Slices)": "655", "7\" Chicken & Basil Pizza (4 Slices)": "300", "9\" Chicken & Basil Pizza (6 Slices)": "510", "12\" Chicken & Basil Pizza (8 Slices)": "655", "7\" Chicken in Fire Pizza (4 Slices)": "300", "9\" Chicken in Fire Pizza (6 Slices)": "510", "12\" Chicken in Fire Pizza (8 Slices)": "655", "7\" Chicken Extreme Pizza (4 Slices)": "300", "9\" Chicken Extreme Pizza (6 Slices)": "510", "12\" Chicken Extreme Pizza (8 Slices)": "655", "7\" Chilliwala Chicken Pizza (4 Slices)": "300", "9\" Chilliwala Chicken Pizza (6 Slices)": "510", "12\" Chilliwala Chicken Pizza (8 Slices)": "655", "7\" Chicken Maxed Out Pizza (4 Slices)": "300", "9\" Chicken Maxed Out Pizza (6 Slices)": "510", "12\" Chicken Maxed Out Pizza (8 Slices)": "655", "Cheesy Dip": "35", "Salsa Dip": "35", "Penne Pasta & Garlic Bread": "190", "Garlic Bread (5 Pcs)": "105", "Cheese Garlic Bread (5 Pcs)": "155", "Paneer Stromboli": "215", "French Fries": "70", "Crostini (Jain) (5 Pcs)": "180", "Crispy Chicken Toast (5 Pcs)": "195", "Chicken Stromboli": "235", "Pizza Box Combo 1": "349", "Veg Hungry Fox Combo": "615", "Pizza Box Combo 2": "379", "Pizza Box Combo 3": "425", "Non-Veg Hungry Fox Combo": "615", "Thums Up (500 ml)": "45", "Thums Up (250 ml)": "23", "Sprite (500 ml)": "45", "Sprite (250 ml)": "23", "Fanta (500 ml)": "45", "Fanta (250 ml)": "23", "Mineral Water (1 ltr)": "20"}