{"Hot and Sour Chicken Soup": "130", "Chicken Manchow Soup": "130", "Mushroom Soup": "110", "Veg Noodles": "100", "Egg Noodles": "130", "Chicken Noodles": "160", "Chilli Chicken": "200", "Chicken 65": "200", "Chicken Manchurian": "200", "RR Chicken": "210", "Hong Kong Chicken": "210", "Dragon Chicken": "220", "Pepper Chicken": "200", "Chicken 555": "210", "Majestic Lollipop": "240", "Kaju Chicken": "240", "Veg Manchurian": "140", "Baby corn 65": "140", "Baby corn Manchurian": "140", "Chilli Paneer": "190", "Paneer 65": "190", "Mushroom 65": "150", "Chilli Mushroom": "150", "Mushroom Manchurian": "150", "Veg Fried Rice": "140", "Special Veg Fried Rice": "190", "Chicken Fried Rice": "200", "Special Chicken Fried Rice": "220", "Mughlai Chicken Fried Rice": "220", "Egg Fried Rice": "170", "Chicken Fry Piece Fried Rice": "230", "Prawns Fried Rice": "230", "Mixed Fried Rice": "250", "Mughlai Mixed Fried Rice": "260", "Egg Mughlai Fried Rice": "180", "Paneer Fried Rice": "190", "Mushroom Fried Rice": "190", "Veg Schezwan Fried Rice ": "180", "Chicken Schezwan Fried Rice ": "190", "Fish Biryani": "210", "Prawns Biryani": "230", "Chilli Wings Biryani": "270", "Mughlai Fry Biryani": "240", "Prawns Mughlai Biryani": "260", "Mixed Biryani": "250", "Mughlai Mixed Biryani": "260", "Chicken Chettinadu Biryani": "220", "Curd Rice": "90", "Chicken Fry Biryani": "230"}