{"Paneer Malai Tikka": "190", "Paneer Tikka": "170", "Mushroom Tikka": "170", "French Fries": "70", "Mixed Veg Pakora": "100", "Paneer Pakora": "120", "Veg Cutlet": "80", "Peanut Masala": "70", "Chana Chat": "80", "Veg Cutlet (2 Pcs)": "80", "Aloo Chat": "80", "Butter Toast": "50", "Veg Sandwich": "60", "Fresh Paneer": "100", "Egg Pakora": "80", "Omelette": "50", "Boiled Egg (2 Pcs)": "30", "Egg Sandwich": "70", "Chicken Malai Tikka": "210", "Roasted Chicken": "200", "Chicken Fry": "220", "Afghani Chicken": "210", "Chilli Potato": "120", "Chilli Honey Potato": "130", "Veg Manchurian": "120", "Chilli Paneer Dry": "150", "Chilli Mushroom Dry": "160", "Veg Fried Rice": "80", "Egg Fried Rice": "100", "Veg Biryani": "80", "Chicken Biryani": "160", "Egg Biryani": "130", "Steamed Rice": "30", "Jeera Rice": "40", "Butter Rice": "50", "Mattar Pulao": "50", "Veg Pulao": "60", "Rice Dal Fry": "80", "Dal Amritsari": "120", "Dal Makhani": "120", "Dal Handi": "110", "Sher E Punjab Dhana Special Dal": "130", "Navratan Korma": "150", "Jeera Aloo": "100", "Chana Masala": "120", "Veg Jalfrezi": "140", "Malai Kofta": "160", "Dilkush Kofta": "170", "Mattar Mushroom": "130", "Mushroom Curry": "130", "Dal Arhar": "90", "Mix Veg": "120", "Kashmiri Dumaloo": "140", "Begun Da Bharath": "80", "Aloo Mattar": "80", "Mattar Paneer": "130", "Palak Paneer": "130", "Shahi Paneer": "150", "Khadi Paneer": "150", "Kaleji Paneer": "160", "Paneer Changezi": "170", "Paneer Rampuri": "150", "Paneer Butter Masala": "170", "Paneer Pasanda": "160", "Paneer Do Pyaza": "160", "Lahori Paneer": "150", "Handi Paneer": "160", "Mughlai Paneer": "160", "Paneer Bhujia": "140", "Afghani Paneer": "170", "Kaju Paneer": "170", "Nawabi Paneer": "180", "Makhani Paneer": "160", "Punjabi Paneer": "170", "Kali Mirchi Paneer": "170", "Tandoori Roti": "10", "Butter Roti": "10", "Plain Naan": "30", "Butter Naan": "40", "Stuff Naan": "50", "Garlic Naan": "50", "Amritsari Naan": "60", "Lachha Paratha": "30", "Missi Roti": "20", "Aloo Paratha": "50", "Stuff Paratha": "50", "Paneer Paratha": "60", "Gobi Paratha": "50", "Mooli Paratha": "50", "Stuff Kulcha": "50", "Paneer Kulcha": "60", "Egg Paratha": "60", "Mineral Water(1ltr)": "30", "Fresh Lime Soda": "25", "Lassi (Salty)": "30", "Lassi (Sweet)": "40", "Green Salad": "40", "Kachumber Salad": "30", "Kheera Salad": "30", "Tomato Salad": "30", "Boondi Raita": "60", "Pineapple Raita": "70", "Plain Curd": "50", "Roasted Papad": "20", "Masala Papad": "40", "Papad Fry": "20", "Fruit Raita": "80", "Mix Raita": "60", "Tomato Soup": "60", "Vegetable Soup": "60"}