{"Aloo Paratha (2 Pcs)": "120", "Gobi Paratha (2 Pcs)": "120", "Mixed Paratha (2 Pcs)": "120", "Paneer Paratha (2 Pcs)": "120", "Veg Green Sandwich": "70", "Veg Cutlet": "100", "Paneer Cutlet": "120", "Chola Bhatoore": "120", "Poori Bhaji": "110", "Onion Salad": "30", "Green Salad": "50", "Kachumber Salad": "60", "Punjabi Salad": "70", "Kimchi Salad": "60", "Fruit Salad": "90", "Russian Salad": "100", "Dahi Kachumber Salad": "70", "Papad Dry": "15", "Papad Dry & Fry Masala": "25", "Papad Dilruba": "80", "Peanut Chaat": "100", "Chana Koliwada": "100", "Chana Roast": "110", "Chana Chaat": "100", "Aloo Chaat": "90", "Veg Pakora": "120", "Kalali Pakora": "120", "Punjabi Pakora": "130", "Paneer Pakora": "150", "Hara Bhara Kebab": "130", "Paneer Butter Masala": "170", "Paneer Kali Mirch": "170", "Paneer Junglee": "180", "Paneer Kadai": "170", "Paneer Achari": "180", "Paneer Angara": "180", "Paneer Shahi": "180", "Paneer Handi": "170", "Paneer Korma": "180", "Paneer Lababdar": "180", "Paneer Pasanda": "190", "Paneer Swad Exotica Special": "240", "Paneer Tikka Masala": "180", "Paneer Mattar": "160", "Paneer Bhurji": "180", "Paneer Kaju": "190", "Paneer Palak": "170", "Kaju Curry": "180", "Kaju Masala": "180", "Navratan Korma": "170", "Veg Kolhapuri": "150", "Veg Jaipuri": "150", "Veg Makhanwala": "150", "Veg Jalfrezi": "160", "Stuffed Tomato": "150", "Stuffed Capsicum": "150", "Methi Mattar Malai": "160", "Methi Malai Papad": "170", "Green Peas Masala": "130", "Aloo Jeera": "130", "Aloo Rasila": "130", "Aloo Banaras": "130", "Aloo Khatta": "140", "Aloo Shimla": "130", "Aloo Palak": "130", "Aloo Methi": "130", "Aloo Gobi Mattar": "130", "Dum Aloo": "150", "Dum Aloo Kashmiri": "160", "Bhindi Masala": "140", "Bhindi Do Pyaza": "140", "Chana Masala": "140", "Corn Palak": "140", "Reshmi Palak": "140", "Palak Mattar": "140", "Sev Tomato": "140", "Sev Palak": "140", "Veg Seekh Kebab Masala": "160", "Baby corn Masala": "160", "Veg Shahi Sona": "170", "Veg Exotica Special": "180", "Mushroom Masala": "160", "Mushroom Paneer": "180", "Mushroom Kadai": "160", "Mushroom Mattar": "160", "Mixed Veg": "140", "Kadai Veg": "140", "Tawa Veg": "150", "Veg Kofta Hariyali": "160", "Veg Malai Kofta": "160", "Veg Zafrani Kofta": "170", "Veg Kofta Queen": "170", "Veg Nargisi Kofta": "170", "Veg Makhmali Kofta": "160", "Dal Fry": "90", "Dal Tadka": "100", "Dal Hariyali": "90", "Dal Maharani": "100", "Dal Makhani": "110", "Dal Kolhapuri": "100", "Dal Exotica Special": "120", "Steamed Rice": "90", "Jeera Rice": "100", "Veg Pulao": "130", "Kashmiri Pulao": "140", "Veg Biryani": "140", "Veg Dum Biryani": "150", "Garlic Fried Rice": "140", "Butter Khichdi": "100", "Curd Rice": "110", "Butter Tawa Roti": "15", "Butter Tandoori Roti": "15", "Plain Tandoori Roti": "12", "Plain Tawa Roti": "12", "Missi Roti": "35", "Butter Naan": "40", "Plain Naan": "40", "Garlic Naan": "50", "Kashmiri Naan": "50", "Butter Stuffed Kulcha": "50", "Plain Kulcha": "40", "Laccha Paratha": "40", "Tawa Paratha": "30", "Aloo Paratha": "60", "Paneer Paratha": "60", "Gobi Paratha": "50", "Stuffed Paratha": "50", "Exotica Special Basket": "220"}