{"Veg Noodles": "40", "Veg Schezwan Noodles": "50", "Egg Noodles": "50", "Egg Schezwan Noodles": "60", "Manchurian Noodles": "90", "Chicken Noodles": "90", "Chicken Manchurian Noodles": "90", "Paneer Noodles": "80", "Chicken Schezwan Noodles": "100", "Paneer Schezwan Noodles": "100", "Mushroom Schezwan Noodles": "100", "Babycorn Noodles": "90", "Veg Manchurian": "60", "Egg Chilli": "60", "Egg Manchurian": "60", "Chicken Manchurian": "100", "Chilli Chicken": "100", "Chicken 65": "100", "Chicken Lollipops (4 Pcs)": "125", "Panner Chilli": "125", "Babycorn Chilli": "125", "Chicken Joints (2 Pcs)": "120", "Chicken Joint Gravy": "120", "Paneer Curry": "100", "Mushroom Curry": "100", "Babycorn Fried Curry": "100", "Mushroom Fried Rice": "100", "Schezwan Chicken Fried Rice": "90", "Veg Schezwan Fried Rice": "75", "Egg Schezwan Fried Rice": "80", "Veg Fried Rice": "65", "Paneer Fried Rice": "90", "Paneer Schezwan Fried Rice": "100", "Mushroom Schezwan Fried Rice": "100", "Chicken Fried Rice": "85", "Egg Fried Rice": "75", "Veg Manchurian Frankie": "60", "Veg Frankie": "30", "Egg Frankie": "40", "Chicken And Egg Frankie": "60", "Paneer Frankie": "60", "Double Egg + Chicken Frankie": "75", "Chicken Manchurian + Egg Frankie": "80", "Veg Frankie + Veg Noodles ": "195", "Veg Fried Rice + Veg Manchurian": "110", "Egg Chilli + Veg Fried Rice": "100", "Veg Fried Rice + Veg Frankie": "80", "Chicken Soup + Egg Noodles": "80", "Chicken Fried Rice Single Serves": "85", "Veg Sweet Corn Soup": "30", "Chicken Sweet Corn Soup": "40", "Chicken Soup (Bone)": "30", "Boneless Chicken Soup": "30", "Water Bottle (1 ltr)": "25", "Coke (250 ml)": "25", "Thums Up (250 ml)": "25"}