{"Veg Cream of Tomato Soup": "159", "Veg Cream of Mushroom Soup": "159", "Veg Manchow Soup": "139", "Veg Hot & Sour Soup": "139", "Veg Sweet corn Soup": "139", "Veg Minestrone Soup": "139", "Veg Lemon Coriander Soup": "139", "Veg Dhaniya Shorba Soup": "149", "Chicken Cream of Tomato Soup": "179", "Chicken Cream of Mushroom Soup": "179", "Chicken Manchow Soup": "149", "Chicken Hot & Sour Soup": "149", "Chicken Sweet corn Soup": "149", "Chicken Minestrone Soup": "149", "Chicken Lemon Coriander Soup": "149", "Chicken Dhaniya Shorba Soup": "159", "Chicken Tikka Salad": "169", "Chicken Caesar Salad": "169", "Veg Pasta": "269", "Veg Lasagne": "269", "Chicken Choice of Pasta": "269", "Chicken Lasagne": "299", "Paneer Tikka Tandoori": "249", "Paneer Pahadi Tandoori": "249", "Paneer Malai Tandoori": "249", "Paneer Achari Tandoori": "249", "Paneer Banjara Tandoor": "249", "Paneer Sholey Kebab": "249", "Mushroom Tandoori": "229", "Aloo Tandoori": "229", "Aloo Ki Nazakat": "229", "Multani Mushroom": "249", "Veg Tandoori Platter": "409", "Murgh Tandoori": "249", "Chicken Garlic Tandoori": "259", "Chicken Tandoori Zumka": "279", "Chicken Mumbai Mirch Kebab": "279", "Chicken Rozali Kebab": "299", "Chicken Dakshini Kebab": "279", "Bhatti Ka Murgh": "279", "Chicken Kalimiri Kebab": "279", "Chicken Sholey Kebab": "279", "Chicken Reshmi Kebab": "279", "Chicken Tangdi Kebab": "279", "Mutton Seekh Kebab": "379", "Non-Veg Tandoori Platter": "709", "Veg Diwani Handi": "229", "Veg Makhanwala": "229", "Veg Kolhapuri": "229", "Dum Aloo Punjabi": "229", "Paneer Tikka Masala": "249", "Paneer Butter Masala": "249", "Paneer Kadai": "249", "Paneer Chatpata": "249", "Palak Paneer": "249", "Paneer Bhurji": "239", "Mushroom Methi Malai Masala": "229", "Baby corn Masala": "229", "Baby corn Methi Masala": "229", "Murgh Musallam": "359", "Butter Chicken": "299", "Chicken Tikka Masala": "279", "Chicken Chatpata": "279", "Chicken Patiala ": "279", "Chicken Peshawari ": "279", "Chicken Lahori": "279", "Chicken Bhuna": "299", "Chicken Masala": "299", "Chicken Hyderabadi Masala": "299", "Chicken Rara Masala": "329", "Chicken Kolhapuri": "299", "Chicken Kalimiri Masala": "299", "Chicken Lehsuni Masala": "299", "Chicken Kadai": "299", "Chicken Handi": "299", "Mutton Rara Masala": "399", "Mutton Bhuna Ghosh": "349", "Mutton Handi": "349", "Mutton Rogan Josh": "349", "Dal Makhani": "189", "Dal Tadka": "169", "Dal Fry": "169", "Dal Lehsuni": "169", "Veg Biryani": "149", "Egg Biryani": "199", "Chicken Dum Biryani": "249", "Chicken Hyderabadi Biryani": "249", "Chicken Lucknowi Biryani": "249", "Chicken Kepsa Biryani": "449", "Steamed Rice": "139", "Jeera Rice": "159", "Dal Khichdi": "179", "Curd Rice": "179", "Green Peas Pulao": "149", "Roti": "39", "Butter Roti": "49", "Naan": "49", "Butter Naan": "59", "Cheese Naan": "99", "Garlic Naan": "119", "Kulcha": "59", "Butter Kulcha": "69", "Stuffed Kulcha": "99", "Paratha": "99", "Mixed Veg Raita": "89", "Boondi Raita": "99", "Pineapple Raita": "99", "Fresh Green Salad": "99", "Veg Crispy": "249", "Veg Manchurian": "249", "Veg Spring Roll": "249", "Veg Schezwan Finger": "249", "Potato Honey Chilli": "249", "Paneer Chilli": "269", "Paneer BBQ 65": "269", "Mushroom Chilli": "279", "Veg Manchurian Chilli": "279", "Chicken Crispy": "289", "Chicken Chilli": "289", "Chicken Lollipop": "289", "Chicken Spring Roll": "289", "Chicken Burnt Garlic": "289", "Chicken Oyster": "299", "Chicken Human Sauce": "299", "Prawns Chilli": "289", "Paneer Chilli Gravy": "259", "Veg Manchurian Gravy": "239", "Chilli Garlic Gravy": "239", "Veg Hunan Sauce": "239", "Thai Green Curry": "269", "Thai Red Curry": "269", "Chicken Chilli Gravy": "269", "Chicken Manchurian Gravy": "269", "Chicken Hunan Sauce": "279", "Chicken Thai Green Curry": "299", "Chicken Thai Red Curry": "299", "Chicken in Oyster Sauce": "279", "Veg Fried Rice": "189", "Veg Schezwan Fried Rice": "199", "Veg Triple Schezwan Rice": "239", "Veg Pot Rice": "229", "Veg Burn Garlic Rice": "189", "Veg Shanghai Fried Rice": "189", "Egg Fried Rice": "199", "Egg Schezwan Fried Rice": "209", "Egg Triple Schezwan Rice": "249", "Egg Pot Rice": "239", "Egg Burnt Garlic Rice": "199", "Egg Shanghai Fried Rice": "199", "Chicken Fried Rice": "219", "Chicken Schezwan Fried Rice": "229", "Chicken Triple Schezwan Rice": "249", "Chicken Pot Rice": "239", "Chicken Burnt Garlic Rice": "209", "Chicken Shanghai Fried Rice": "209", "Mixed Fried Rice": "239", "Mixed Schezwan Fried Rice": "259", "Mixed Burn Garlic Rice": "239", "Mixed Shanghai Fried Rice": "239", "Veg Hakka Noodles": "179", "Veg Schezwan Noodles": "179", "Veg Pan Fried Rice Noodles": "179", "Egg Hakka Noodles": "189", "Egg Schezwan Noodles": "189", "Egg Pan Fried Rice Noodles": "189", "Chicken Hakka Noodles": "209", "Chicken Schezwan Noodles": "209", "Chicken Pan Fried Rice Noodles": "209", "Mixed Hakka Noodles": "239", "Mixed Schezwan Noodles": "239", "Mixed Pan Fried Rice Noodles": "239", "Veg Dum Biryani (1 Kg)": "899", "Chicken Dum Biryani (1 Kg)": "1199", "Chicken Tikka Biryani (1 Kg)": "1299", "Mutton Dum Biryani (1 Kg)": "1399", "Gulab Jamun": "99", "Caramel Custard": "119", "Brownie": "169"}